LICENSE
MANIFEST.in
README.md
README.rst
setup.py
mw_aiohttp_session/__init__.py
mw_aiohttp_session/redis_storage.py
mw_aiohttp_session.egg-info/PKG-INFO
mw_aiohttp_session.egg-info/SOURCES.txt
mw_aiohttp_session.egg-info/dependency_links.txt
mw_aiohttp_session.egg-info/requires.txt
mw_aiohttp_session.egg-info/top_level.txt