Metadata-Version: 2.1
Name: mw-aiohttp-session
Version: 0.1.12
Summary: maxwin aiohttp-session 
Home-page: https://bitbucket.org/maxwin-inc/mw-aiohttp-session/src
Author: candyabc
Author-email: hfcandyabc@163.com
Classifier: Intended Audience :: Developers
Classifier: License :: OSI Approved :: BSD License
Classifier: Operating System :: OS Independent
Classifier: Programming Language :: Python :: 3.6
License-File: LICENSE
